setup.py
GNota/SimpleGladeApp.py
GNota/__init__.py
GNota/controller.py
GNota/default_db.py
GNota/gnota
GNota/gnota_exceptions.py
GNota/main.py
GNota/model.py
GNota/nosy.py
GNota/populate.py
GNota/test.py
GNota.egg-info/PKG-INFO
GNota.egg-info/SOURCES.txt
GNota.egg-info/dependency_links.txt
GNota.egg-info/not-zip-safe
GNota.egg-info/requires.txt
GNota.egg-info/top_level.txt
