Metadata-Version: 1.0
Name: GNota
Version: 0.1.0-2
Summary: GNota is a gradebook software used to manage students and automate score calculations. gNota has some basic student data archiving (such as Phone Number, notes about academic or behavioral problems, missed classes) and an advanced score calculation system. It can use a variety of score systems (for instance, A-F or 0-100) and implements various average algorithms (arithmetic average, weighted averages, average of best N scores). 
Home-page: https://launchpad.net/gnota
Author: Leandro Lameiro
Author-email: lameiro@gmail.com
License: GPLv3
Keywords: school gradebook
Platform: UNKNOWN
